Automatic_Feature_Engineering/__init__.py
Automatic_Feature_Engineering/featureEngineering.py
Automatic_Feature_Engineering-0.3.0.dist-info/License
Automatic_Feature_Engineering-0.3.0.dist-info/METADATA
Automatic_Feature_Engineering-0.3.0.dist-info/WHEEL
Automatic_Feature_Engineering-0.3.0.dist-info/top_level.txt
Automatic_Feature_Engineering-0.3.0.dist-info/RECORD
