Metadata-Version: 2.1
Name: Automatic_Feature_Engineering
Version: 0.3.0
Summary: A package for automated feature engineering with support for categorical and numerical data
Home-page: https://github.com/sagarsambhwani/AutoFeatureEngineering
Author: Sagar Sambhwani
Author-email: sagar.2001.a20@gmail.com
Classifier: Programming Language :: Python :: 3
Classifier: License :: OSI Approved :: MIT License
Classifier: Operating System :: OS Independent
Requires-Python: >=3.7
License-File: License
Requires-Dist: pandas
Requires-Dist: scikit-learn
Requires-Dist: category-encoders
Requires-Dist: numpy
Requires-Dist: tsfresh
